pyzil/__init__.py
pyzil/account.py
pyzil/contract.py
pyzil/pow.py
pyzil/common/__init__.py
pyzil/common/local.py
pyzil/common/utils.py
pyzil/crypto/__init__.py
pyzil/crypto/bech32.py
pyzil/crypto/drbg.py
pyzil/crypto/schnorr.py
pyzil/crypto/tools.py
pyzil/crypto/zilkey.py
pyzil/tests/test_account.py
pyzil/tests/test_chain.py
pyzil/tests/test_contract.py
pyzil/tests/test_lowlevel_api.py
pyzil/tests/test_pow.py
pyzil/tests/test_units.py
pyzil/tests/crypto/address.fixtures.ts
pyzil/tests/crypto/bech32.fixtures.json
pyzil/tests/crypto/checksum.fixtures.ts
pyzil/tests/crypto/hmac_drbg.rsp
pyzil/tests/crypto/keypairs.fixtures.ts
pyzil/tests/crypto/mykey.txt
pyzil/tests/crypto/mykey2.txt
pyzil/tests/crypto/mykey3.txt
pyzil/tests/crypto/schnorr.fixtures.json
pyzil/tests/crypto/test_drbg.py
pyzil/tests/crypto/test_schnorr.py
pyzil/tests/crypto/test_zilkey.py
pyzil/tests/crypto/zilliqa_keystore.json
pyzil/tests/crypto/zilliqa_keystore2.json
pyzil/zilliqa/__init__.py
pyzil/zilliqa/api.py
pyzil/zilliqa/chain.py
pyzil/zilliqa/node.py
pyzil/zilliqa/units.py
pyzil/zilliqa/proto/__init__.py
pyzil/zilliqa/proto/messages_pb2.py
pyzil-1.5.22.dist-info/LICENSE
pyzil-1.5.22.dist-info/METADATA
pyzil-1.5.22.dist-info/WHEEL
pyzil-1.5.22.dist-info/top_level.txt
pyzil-1.5.22.dist-info/RECORD
