Metadata-Version: 2.1
Name: pyzil
Version: 1.5.22
Summary: Zilliqa Python API
Home-page: http://github.com/deepgully/pyzil
Author: Gully Chen
Author-email: deepgully@gmail.com
License: MIT License
Keywords: zilliqa api
Platform: UNKNOWN
Classifier: Development Status :: 3 - Alpha
Classifier: Programming Language :: Python
Classifier: License :: OSI Approved :: MIT License
Requires-Dist: requests
Requires-Dist: jsonrpcclient
Requires-Dist: jsonrpcclient[requests]
Requires-Dist: protobuf
Requires-Dist: fastecdsa
Requires-Dist: pyethash
Requires-Dist: pycryptodome
Requires-Dist: eth-hash[pycryptodome]
